{
  "name": "movies-explorer-api",
  "version": "1.0.0",
  "description": "",
  "main": "app.js",
  "scripts": {
    "lint": "npx eslint .",
    "start": "node app.js",
    "dev": "nodemon app.js"
  },
  "repository": {
    "type": "git",
    "url": "git+https://github.com/natalai2410/movies-explorer-api.git"
  },
  "author": "Kryukova Natalia",
  "license": "ISC",
  "bugs": {
    "url": "https://github.com/natalai2410/movies-explorer-api/issues"
  },
  "homepage": "https://github.com/natalai2410/movies-explorer-api#readme",
  "dependencies": {
    "express": "^4.18.2",
    "mongoose": "^6.6.5"
  },
  "devDependencies": {
    "eslint": "8.22.0",
    "eslint-plugin-react": "^7.31.9",
    "nodemon": "^2.0.20"
  }
}
